static_compress/__init__.py
static_compress/compressors.py
static_compress/mixin.py
static_compress/storage.py
test/__init__.py
test/test_compressors.py
django_static_compress-2.1.0.dist-info/LICENSE
django_static_compress-2.1.0.dist-info/METADATA
django_static_compress-2.1.0.dist-info/WHEEL
django_static_compress-2.1.0.dist-info/top_level.txt
django_static_compress-2.1.0.dist-info/RECORD
